azure/maps/timezone/__init__.py
azure/maps/timezone/_client.py
azure/maps/timezone/_configuration.py
azure/maps/timezone/_enums.py
azure/maps/timezone/_patch.py
azure/maps/timezone/_serialization.py
azure/maps/timezone/_version.py
azure/maps/timezone/py.typed
azure/maps/timezone/aio/__init__.py
azure/maps/timezone/aio/_client.py
azure/maps/timezone/aio/_configuration.py
azure/maps/timezone/aio/_patch.py
azure/maps/timezone/aio/operations/__init__.py
azure/maps/timezone/aio/operations/_operations.py
azure/maps/timezone/aio/operations/_patch.py
azure/maps/timezone/operations/__init__.py
azure/maps/timezone/operations/_operations.py
azure/maps/timezone/operations/_patch.py
azure_maps_timezone-1.0.0b1.dist-info/METADATA
azure_maps_timezone-1.0.0b1.dist-info/WHEEL
azure_maps_timezone-1.0.0b1.dist-info/top_level.txt
azure_maps_timezone-1.0.0b1.dist-info/RECORD
